formation/__init__.py
formation/apps.py
formation/models.py
formation/urls.py
formation/utils.py
formation/views.py
formation/wagtail_hooks.py
formation/widgets.py
formation/blocks/__init__.py
formation/blocks/fields.py
formation/blocks/forms.py
formation/static/js/formation.js
formation/templates/formation/reusable_form.html
formation/templates/formation/blocks/base_field.html
formation/templates/formation/blocks/base_form.html
formation/templates/formation/blocks/boolean_field.html
formation/templates/formation/blocks/date_field.html
formation/templates/formation/blocks/datetime_field.html
formation/templates/formation/blocks/email_field.html
formation/templates/formation/blocks/file_field.html
formation/templates/formation/blocks/integer_field.html
formation/templates/formation/blocks/radio_field.html
formation/templates/formation/blocks/select_field.html
formation/templates/formation/blocks/submit_button.html
formation/templates/formation/blocks/text_field.html
formation/templates/formation/blocks/textarea_field.html
formation/templatetags/__init__.py
formation/templatetags/formation_tags.py
wagtail_formation-0.2.1.dist-info/licenses/LICENSE
wagtail_formation-0.2.1.dist-info/METADATA
wagtail_formation-0.2.1.dist-info/WHEEL
wagtail_formation-0.2.1.dist-info/top_level.txt
wagtail_formation-0.2.1.dist-info/RECORD
