Metadata-Version: 2.4
Name: wagtail_formation
Version: 0.2.1
Summary: Build forms from wagtail blocks
Home-page: https://github.com/mwesterhof/wagtail_formation
Author: Marco Westerhof
Author-email: m.westerhof@lukkien.com
License: MIT license
Keywords: wagtail_formation
Classifier: Development Status :: 2 - Pre-Alpha
Classifier: Intended Audience :: Developers
Classifier: License :: OSI Approved :: MIT License
Classifier: Natural Language :: English
Classifier: Programming Language :: Python :: 3
Classifier: Programming Language :: Python :: 3.10
Classifier: Programming Language :: Python :: 3.11
Classifier: Programming Language :: Python :: 3.12
Requires-Python: >=3.10
License-File: LICENSE
Requires-Dist: cryptography==46.0.1
Requires-Dist: wagtail-generic-chooser==0.7
Dynamic: author
Dynamic: author-email
Dynamic: classifier
Dynamic: description
Dynamic: home-page
Dynamic: keywords
Dynamic: license
Dynamic: license-file
Dynamic: requires-dist
Dynamic: requires-python
Dynamic: summary
